flask_authgen_jwt.py
Flask_authgen_jwt-4.2.3.dist-info/LICENSE
Flask_authgen_jwt-4.2.3.dist-info/METADATA
Flask_authgen_jwt-4.2.3.dist-info/WHEEL
Flask_authgen_jwt-4.2.3.dist-info/top_level.txt
Flask_authgen_jwt-4.2.3.dist-info/RECORD
