Metadata-Version: 2.1
Name: Flask-authgen-jwt
Version: 4.2.3
Summary: JWT authentication and generator for Flask routes
Home-page: https://github.com/dmtzs/Flask-authgen-jwt
Author: Diego Martinez
Author-email: gd-code@outlook.com
License: MIT
Project-URL: Bug Tracker, https://github.com/dmtzs/Flask-authgen-jwt/issues
Classifier: Environment :: Web Environment
Classifier: Intended Audience :: Developers
Classifier: Programming Language :: Python :: 3
Classifier: Programming Language :: Python :: Implementation :: MicroPython
Classifier: License :: OSI Approved :: MIT License
Classifier: Operating System :: OS Independent
License-File: LICENSE
Requires-Dist: Flask
Requires-Dist: PyJWT
